gcp_scanner/__init__.py
gcp_scanner/__main__.py
gcp_scanner/arguments.py
gcp_scanner/credsdb.py
gcp_scanner/error_handler.py
gcp_scanner/models.py
gcp_scanner/scanner.py
gcp_scanner/client/__init__.py
gcp_scanner/client/appengine_client.py
gcp_scanner/client/bigquery_client.py
gcp_scanner/client/bigtable_client.py
gcp_scanner/client/client_factory.py
gcp_scanner/client/cloud_billing_client.py
gcp_scanner/client/cloud_functions_client.py
gcp_scanner/client/cloud_resource_manager_client.py
gcp_scanner/client/compute_client.py
gcp_scanner/client/datastore_client.py
gcp_scanner/client/dns_client.py
gcp_scanner/client/domains_client.py
gcp_scanner/client/filestore_client.py
gcp_scanner/client/firestore_client.py
gcp_scanner/client/iam_client.py
gcp_scanner/client/interface_client.py
gcp_scanner/client/kms_client.py
gcp_scanner/client/pubsub_client.py
gcp_scanner/client/service_management_client.py
gcp_scanner/client/serviceusage_client.py
gcp_scanner/client/sourcerepo_client.py
gcp_scanner/client/spanner_client.py
gcp_scanner/client/sql_client.py
gcp_scanner/client/storage_client.py
gcp_scanner/crawler/__init__.py
gcp_scanner/crawler/app_services_crawler.py
gcp_scanner/crawler/bigquery_crawler.py
gcp_scanner/crawler/bigtable_instances_crawler.py
gcp_scanner/crawler/cloud_billing_account_crawler.py
gcp_scanner/crawler/cloud_functions_crawler.py
gcp_scanner/crawler/cloud_resource_manager_iam_policy_crawler.py
gcp_scanner/crawler/cloud_resource_manager_project_info_crawler.py
gcp_scanner/crawler/cloud_resource_manager_project_list_crawler.py
gcp_scanner/crawler/compute_disks_crawler.py
gcp_scanner/crawler/compute_firewall_rules_crawler.py
gcp_scanner/crawler/compute_images_crawler.py
gcp_scanner/crawler/compute_instances_crawler.py
gcp_scanner/crawler/compute_security_policies_crawler.py
gcp_scanner/crawler/compute_snapshots_crawler.py
gcp_scanner/crawler/compute_static_ips_crawler.py
gcp_scanner/crawler/compute_subnets_crawler.py
gcp_scanner/crawler/crawler_factory.py
gcp_scanner-1.4.0.dist-info/LICENSE
gcp_scanner-1.4.0.dist-info/METADATA
gcp_scanner-1.4.0.dist-info/WHEEL
gcp_scanner-1.4.0.dist-info/entry_points.txt
gcp_scanner-1.4.0.dist-info/top_level.txt
gcp_scanner-1.4.0.dist-info/RECORD
