Metadata-Version: 2.1
Name: gcp-scanner
Version: 1.4.0
Summary: GCP resource scanner that can help determine what level of access certain credentials possess on GCP
License: Apache License
Project-URL: Homepage, https://github.com/google/gcp_scanner
Keywords: gcp,scan,access,security-tool,python
Classifier: Programming Language :: Python :: 3
Requires-Python: >=3.7
License-File: LICENSE
Requires-Dist: pyu2f ==0.1.5
Requires-Dist: google-api-python-client ==2.80.0
Requires-Dist: google-cloud-container ==2.17.4
Requires-Dist: google-cloud-iam ==2.11.2
Requires-Dist: httplib2 ==0.21.0
Requires-Dist: requests ==2.31.0
